demo_package/__init__.py
demo_package/utils/__init__.py
demo_package/utils/aws_utils.py
demo_package/utils/common_utils.py
demo_package/utils/google_utils.py
pycam_demo_package-0.1.0.dist-info/LICENSE
pycam_demo_package-0.1.0.dist-info/METADATA
pycam_demo_package-0.1.0.dist-info/WHEEL
pycam_demo_package-0.1.0.dist-info/top_level.txt
pycam_demo_package-0.1.0.dist-info/RECORD
