Metadata-Version: 2.1
Name: pycam-demo-package
Version: 0.1.0
Summary: Demo package for Python packaging
Home-page: https://github.com/Edmond22-prog/demo-package
Author: Edmond Makolle
Author-email: edghimakoll@gmail.com
License: MIT License
Classifier: Programming Language :: Python :: 3
Classifier: License :: OSI Approved :: MIT License
Classifier: Operating System :: OS Independent
Requires-Python: >=3.10
License-File: LICENSE
